{
  "generated_utc": "2026-07-01 13:55:14",
  "entries": [
    {
      "ticker": "NVDA",
      "name": "NVDA",
      "added": "2026-07-01",
      "last_checked": "2026-07-01",
      "status": "fit",
      "type": "high-vol trender",
      "vol_tier": "volatile",
      "momentum": "up (+27%)",
      "fair_value": "\u2014",
      "last_earnings": "\u2014",
      "strategies": [
        {
          "name": "Buy & hold",
          "verdict": "Sharpe +1.24"
        }
      ],
      "notes": "vol 51%, ~$939M/day"
    },
    {
      "ticker": "KO",
      "name": "KO",
      "added": "2026-07-01",
      "last_checked": "2026-07-01",
      "status": "fit",
      "type": "stable compounder",
      "vol_tier": "stable",
      "momentum": "up (+18%)",
      "fair_value": "\u2014",
      "last_earnings": "\u2014",
      "strategies": [
        {
          "name": "Buy & hold",
          "verdict": "Sharpe +0.79"
        }
      ],
      "notes": "vol 17%, ~$75M/day"
    },
    {
      "ticker": "AAPL",
      "name": "AAPL",
      "added": "2026-07-01",
      "last_checked": "2026-07-01",
      "status": "fit",
      "type": "trend candidate",
      "vol_tier": "medium",
      "momentum": "up (+42%)",
      "fair_value": "\u2014",
      "last_earnings": "\u2014",
      "strategies": [
        {
          "name": "Buy & hold",
          "verdict": "Sharpe +0.82"
        }
      ],
      "notes": "vol 29%, ~$442M/day"
    },
    {
      "ticker": "INTC",
      "name": "INTC",
      "added": "2026-07-01",
      "last_checked": "2026-07-01",
      "status": "fit",
      "type": "high-vol trender",
      "vol_tier": "volatile",
      "momentum": "up (+524%)",
      "fair_value": "\u2014",
      "last_earnings": "\u2014",
      "strategies": [
        {
          "name": "DualMomentum 12mo",
          "verdict": "Sharpe +0.98 vs B&H +0.64, maxDD -16%"
        },
        {
          "name": "Buy & hold",
          "verdict": "Sharpe +0.64"
        }
      ],
      "notes": "vol 50%, ~$367M/day"
    }
  ]
}